gabi_distribution
