Metadata-Version: 1.0
Name: gabi-distribution
Version: 0.6
Summary: Gaussian and Binomial distributions
Home-page: UNKNOWN
Author: Anukool Rathi
Author-email: Anukool.rathi10@gmail.com
License: UNKNOWN
Platform: UNKNOWN
